LICENSE
MANIFEST.in
README.rst
setup.cfg
setup.py
ghostbuster/__init__.py
ghostbuster/cli.py
ghostbuster/scan.py
ghostbuster/version.py
ghostbuster.egg-info/PKG-INFO
ghostbuster.egg-info/SOURCES.txt
ghostbuster.egg-info/dependency_links.txt
ghostbuster.egg-info/entry_points.txt
ghostbuster.egg-info/requires.txt
ghostbuster.egg-info/top_level.txt