Metadata-Version: 2.1
Name: ghostbuster
Version: 0.0.6
Summary: Eliminate dangling elastic IPs by performing analysis on your resources within all your AWS accounts.
Home-page: https://github.com/assetnote/ghostbuster
Author: shubham_shah
Author-email: sshah@assetnote.io
License: Apache Software License 2.0
Download-URL: https://github.com/assetnote/ghostbuster/archive/0.0.6.tar.gz
Platform: UNKNOWN
Classifier: Development Status :: 3 - Alpha
Classifier: Intended Audience :: Developers
Classifier: Topic :: Software Development :: Libraries
Classifier: License :: OSI Approved :: GNU Affero General Public License v3
Classifier: Programming Language :: Python :: 3.8
Requires-Python: >=0.0.1
License-File: LICENSE
